{
  "$schema": "https://json-schema.org/draft/2020-12/schema",
  "$id": "attributes.hazard.schema.json",
  "title": "Hazard Attribute Schema",
  "description": "Attribute schema for Properties table in Hazard entities.",
  "type": "object",
  "required": [],
  "properties": {
    "concern_class": {
      "type": "string",
      "enum": [
        "safety",
        "security",
        "operational",
        "financial",
        "privacy"
      ]
    },
    "tlp": {
      "type": "string",
      "enum": [
        "TLP:WHITE",
        "TLP:GREEN",
        "TLP:AMBER",
        "TLP:RED"
      ],
      "default": "TLP:WHITE"
    },
    "classification_scheme": {
      "type": "string"
    },
    "classification_code": {
      "type": "string"
    }
  },
  "additionalProperties": true
}
